ansible_deployment/__init__.py
ansible_deployment/class_skeleton.py
ansible_deployment/cli.py
ansible_deployment/cli_autocomplete.py
ansible_deployment/cli_helpers.py
ansible_deployment/config.py
ansible_deployment/deployment.py
ansible_deployment/deployment_dir.py
ansible_deployment/deployment_repo.py
ansible_deployment/deployment_vault.py
ansible_deployment/exceptions.py
ansible_deployment/inventory.py
ansible_deployment/inventory_plugins/__init__.py
ansible_deployment/inventory_plugins/helpers/__init__.py
ansible_deployment/inventory_plugins/helpers/vault.py
ansible_deployment/inventory_plugins/inventory_plugin.py
ansible_deployment/inventory_plugins/inventory_sources/__init__.py
ansible_deployment/inventory_plugins/inventory_sources/local.py
ansible_deployment/inventory_plugins/inventory_sources/terraform.py
ansible_deployment/inventory_plugins/inventory_sources/vault.py
ansible_deployment/inventory_plugins/inventory_writers/__init__.py
ansible_deployment/inventory_plugins/inventory_writers/vault.py
ansible_deployment/playbook.py
ansible_deployment/role.py
ansible_deployment/ssh.py
ansible_deployment/templates/playbook.yml.j2
ansible_deployment-1.0.3.dist-info/LICENSE
ansible_deployment-1.0.3.dist-info/WHEEL
ansible_deployment-1.0.3.dist-info/entry_points.txt
ansible_deployment-1.0.3.dist-info/METADATA
ansible_deployment-1.0.3.dist-info/RECORD
